unionml/__init__.py
unionml/_logging.py
unionml/cli.py
unionml/dataset.py
unionml/defaults.py
unionml/exceptions.py
unionml/fastapi.py
unionml/model.py
unionml/py.typed
unionml/remote.py
unionml/schedule.py
unionml/task_resolver.py
unionml/tracker.py
unionml/type_guards.py
unionml/utils.py
unionml/services/__init__.py
unionml/services/bentoml.py
unionml/templates/basic/cookiecutter.json
unionml/templates/basic/hooks/post_gen_project.py
unionml/templates/basic/hooks/pre_gen_project.py
unionml/templates/basic/{{cookiecutter.app_name}}/.gitignore
unionml/templates/basic/{{cookiecutter.app_name}}/Dockerfile
unionml/templates/basic/{{cookiecutter.app_name}}/README.md
unionml/templates/basic/{{cookiecutter.app_name}}/app.py
unionml/templates/basic/{{cookiecutter.app_name}}/requirements.txt
unionml/templates/basic/{{cookiecutter.app_name}}/data/sample_features.json
unionml/templates/basic-aws-lambda/cookiecutter.json
unionml/templates/basic-aws-lambda/hooks/post_gen_project.py
unionml/templates/basic-aws-lambda/hooks/pre_gen_project.py
unionml/templates/basic-aws-lambda/{{cookiecutter.app_name}}/.gitignore
unionml/templates/basic-aws-lambda/{{cookiecutter.app_name}}/Dockerfile
unionml/templates/basic-aws-lambda/{{cookiecutter.app_name}}/Dockerfile.awslambda
unionml/templates/basic-aws-lambda/{{cookiecutter.app_name}}/README.md
unionml/templates/basic-aws-lambda/{{cookiecutter.app_name}}/app.py
unionml/templates/basic-aws-lambda/{{cookiecutter.app_name}}/requirements.txt
unionml/templates/basic-aws-lambda/{{cookiecutter.app_name}}/template.yaml
unionml/templates/basic-aws-lambda/{{cookiecutter.app_name}}/data/sample_features.json
unionml/templates/basic-aws-lambda/{{cookiecutter.app_name}}/events/event.json
unionml/templates/basic-aws-lambda/{{cookiecutter.app_name}}/tests/__init__.py
unionml/templates/basic-aws-lambda/{{cookiecutter.app_name}}/tests/unit/__init__.py
unionml/templates/basic-aws-lambda/{{cookiecutter.app_name}}/tests/unit/test_handler.py
unionml-0.2.1.dist-info/LICENSE
unionml-0.2.1.dist-info/METADATA
unionml-0.2.1.dist-info/WHEEL
unionml-0.2.1.dist-info/entry_points.txt
unionml-0.2.1.dist-info/top_level.txt
unionml-0.2.1.dist-info/RECORD
