Metadata-Version: 2.1
Name: unionml
Version: 0.2.1
Summary: The easiest way to build and deploy machine learning microservices.
Home-page: https://github.com/unionai-oss/unionml/
Author: unionai-oss
Author-email: info@union.ai
License: Apache
Project-URL: Documentation, https://unionml.readthedocs.io/
Project-URL: Source Code, https://github.com/unionai-oss/unionml/
Project-URL: Issue Tracker, https://github.com/unionai-oss/unionml/issues
Keywords: machine-learning,artificial-intelligence,microservices
Platform: any
Classifier: Development Status :: 4 - Beta
Classifier: Operating System :: OS Independent
Classifier: License :: OSI Approved :: Apache Software License
Classifier: Intended Audience :: Science/Research
Classifier: Intended Audience :: Developers
Classifier: Programming Language :: Python
Classifier: Programming Language :: Python :: 3
Classifier: Programming Language :: Python :: 3.7
Classifier: Programming Language :: Python :: 3.8
Classifier: Programming Language :: Python :: 3.9
Classifier: Programming Language :: Python :: 3.10
Classifier: Topic :: Scientific/Engineering :: Artificial Intelligence
Classifier: Topic :: Software Development :: Libraries :: Application Frameworks
Requires-Python: >=3.7
License-File: LICENSE
Requires-Dist: click
Requires-Dist: cookiecutter
Requires-Dist: dataclasses-json
Requires-Dist: docker
Requires-Dist: fastapi
Requires-Dist: flytekit (>=1.1.0)
Requires-Dist: gitpython
Requires-Dist: joblib
Requires-Dist: mangum
Requires-Dist: numpy
Requires-Dist: pandas
Requires-Dist: pydantic
Requires-Dist: rich (>=11.2.0)
Requires-Dist: scikit-learn
Requires-Dist: typer
Requires-Dist: typing-extensions (>=4.3.0)
Requires-Dist: uvicorn
Requires-Dist: importlib-metadata ; python_version < "3.8"
Provides-Extra: bentoml
Requires-Dist: bentoml (>=1.0.10) ; extra == 'bentoml'
